CHANGES.md
LICENSE
MANIFEST.in
README.md
setup.cfg
setup.py
salut/__init__.py
salut/core.py
salut/version.py
salut.egg-info/PKG-INFO
salut.egg-info/SOURCES.txt
salut.egg-info/dependency_links.txt
salut.egg-info/requires.txt
salut.egg-info/top_level.txt