Metadata-Version: 1.0
Name: salut
Version: 0.1.3
Summary: Gevent based wrapper for pybonjour
Home-page: https://github.com/looplab/salut
Author: Max Persson
Author-email: max@looplab.se
License: Apache License 2.0
Platform: UNKNOWN
Classifier: Development Status :: 4 - Beta
Classifier: Environment :: Console
Classifier: Intended Audience :: Developers
Classifier: License :: OSI Approved :: Apache Software License
Classifier: Programming Language :: Python
Classifier: Programming Language :: Python :: 2
Classifier: Programming Language :: Python :: 2.6
Classifier: Topic :: Software Development :: Libraries :: Python Modules
Classifier: Topic :: System :: Networking
